tests/__init__.py
tests/test_unquote.py
unquotemail/__init__.py
unquotemail/__version__.py
unquotemail/unquote.py
unquotemail/utils.py
unquotemail-1.0.8.dist-info/licenses/LICENSE
unquotemail-1.0.8.dist-info/METADATA
unquotemail-1.0.8.dist-info/WHEEL
unquotemail-1.0.8.dist-info/top_level.txt
unquotemail-1.0.8.dist-info/RECORD
