Metadata-Version: 2.4
Name: unquotemail
Version: 1.0.8
Summary: Parse a given Html/Text email and return only the new text, without the quoted part.
Home-page: https://github.com/getfernand/unquotemail
Author: Cyril Nicodeme
Author-email: contact@cnicodeme.com
License: MIT
Project-URL: Source, https://github.com/getfernand/unquotemail
Keywords: mail email parse parser unquote reply eml
Platform: any
Classifier: Development Status :: 5 - Production/Stable
Classifier: Intended Audience :: Developers
Classifier: Topic :: Communications :: Email
Classifier: Topic :: Internet :: WWW/HTTP :: Dynamic Content
Classifier: Topic :: Software Development :: Libraries :: Python Modules
Classifier: Topic :: Utilities
Classifier: Topic :: Scientific/Engineering :: Interface Engine/Protocol Translator
Classifier: Topic :: Text Processing
Classifier: Operating System :: OS Independent
Classifier: Programming Language :: Python
Classifier: Programming Language :: Python :: 3
Classifier: Programming Language :: Python :: 3.3
Classifier: Programming Language :: Python :: 3.4
Classifier: Programming Language :: Python :: 3.5
Classifier: Programming Language :: Python :: 3.6
Classifier: Programming Language :: Python :: 3.7
Classifier: Programming Language :: Python :: 3.8
Classifier: Programming Language :: Python :: 3.9
Classifier: Programming Language :: Python :: 3.10
Classifier: Programming Language :: Python :: 3.11
Classifier: Programming Language :: Python :: Implementation :: PyPy
Requires-Python: >=3.3, <4
License-File: LICENSE
Requires-Dist: beautifulsoup4>=4.13.3
Requires-Dist: Markdown>=3.7
Requires-Dist: html2text>=2024.2.26
Provides-Extra: dev
Requires-Dist: pytest>=8.3.4; extra == "dev"
Dynamic: author
Dynamic: author-email
Dynamic: classifier
Dynamic: description
Dynamic: description-content-type
Dynamic: home-page
Dynamic: keywords
Dynamic: license
Dynamic: license-file
Dynamic: platform
Dynamic: project-url
Dynamic: provides-extra
Dynamic: requires-dist
Dynamic: requires-python
Dynamic: summary
